pyvider/__init__.py
pyvider/py.typed
pyvider/rpcplugin/__init__.py
pyvider/rpcplugin/_version.py
pyvider/rpcplugin/config.py
pyvider/rpcplugin/defaults.py
pyvider/rpcplugin/exception.py
pyvider/rpcplugin/factories.py
pyvider/rpcplugin/health_servicer.py
pyvider/rpcplugin/py.typed
pyvider/rpcplugin/telemetry.py
pyvider/rpcplugin/types.py
pyvider/rpcplugin/client/__init__.py
pyvider/rpcplugin/client/connection.py
pyvider/rpcplugin/client/core.py
pyvider/rpcplugin/client/handshake.py
pyvider/rpcplugin/client/process.py
pyvider/rpcplugin/client/py.typed
pyvider/rpcplugin/client/types.py
pyvider/rpcplugin/config/__init__.py
pyvider/rpcplugin/config/configure.py
pyvider/rpcplugin/config/manager.py
pyvider/rpcplugin/config/runtime.py
pyvider/rpcplugin/config/validators.py
pyvider/rpcplugin/handshake/__init__.py
pyvider/rpcplugin/handshake/core.py
pyvider/rpcplugin/handshake/negotiation.py
pyvider/rpcplugin/protocol/__init__.py
pyvider/rpcplugin/protocol/base.py
pyvider/rpcplugin/protocol/grpc_broker_pb2.py
pyvider/rpcplugin/protocol/grpc_broker_pb2.pyi
pyvider/rpcplugin/protocol/grpc_broker_pb2_grpc.py
pyvider/rpcplugin/protocol/grpc_controller_pb2.py
pyvider/rpcplugin/protocol/grpc_controller_pb2.pyi
pyvider/rpcplugin/protocol/grpc_controller_pb2_grpc.py
pyvider/rpcplugin/protocol/grpc_stdio_pb2.py
pyvider/rpcplugin/protocol/grpc_stdio_pb2.pyi
pyvider/rpcplugin/protocol/grpc_stdio_pb2_grpc.py
pyvider/rpcplugin/protocol/py.typed
pyvider/rpcplugin/protocol/service.py
pyvider/rpcplugin/server/__init__.py
pyvider/rpcplugin/server/core.py
pyvider/rpcplugin/server/network.py
pyvider/rpcplugin/transport/__init__.py
pyvider/rpcplugin/transport/base.py
pyvider/rpcplugin/transport/py.typed
pyvider/rpcplugin/transport/tcp.py
pyvider/rpcplugin/transport/types.py
pyvider/rpcplugin/transport/unix/__init__.py
pyvider/rpcplugin/transport/unix/transport.py
pyvider/rpcplugin/transport/unix/utils.py
pyvider_rpcplugin-0.0.1000.dist-info/licenses/LICENSE
pyvider_rpcplugin-0.0.1000.dist-info/METADATA
pyvider_rpcplugin-0.0.1000.dist-info/WHEEL
pyvider_rpcplugin-0.0.1000.dist-info/top_level.txt
pyvider_rpcplugin-0.0.1000.dist-info/RECORD
