Metadata-Version: 2.4
Name: pyvider-rpcplugin
Version: 0.0.1000
Summary: Pyvider RPC Plugin
Author-email: Tim Perkins <code@tim.life>
License-Expression: Apache-2.0
Requires-Python: >=3.11
License-File: LICENSE
Requires-Dist: attrs>=25.1.0
Requires-Dist: cryptography>=44.0.1
Requires-Dist: google>=3.0.0
Requires-Dist: grpcio>=1.75.1
Requires-Dist: grpcio-health-checking>=1.73.0
Requires-Dist: protobuf>=5.29.3
Requires-Dist: provide-foundation
Requires-Dist: structlog>=25.1.0
Provides-Extra: test
Requires-Dist: grpc-stubs>=1.53.0.6; extra == "test"
Requires-Dist: grpcio-tools>=1.73.0; extra == "test"
Requires-Dist: types-grpcio>=1.0.0.20250603; extra == "test"
Requires-Dist: types-protobuf>=6.30.2.20250516; extra == "test"
Dynamic: license-file
